pylmod/__init__.py
pylmod/base.py
pylmod/exceptions.py
pylmod/gradebook.py
pylmod/membership.py
pylmod/tests/__init__.py
pylmod/tests/common.py
pylmod/tests/test_base.py
pylmod/tests/test_gradebook.py
pylmod/tests/test_membership.py
pylmod/tests/test_module.py
pylmod-1.0.2.dist-info/LICENSE
pylmod-1.0.2.dist-info/METADATA
pylmod-1.0.2.dist-info/WHEEL
pylmod-1.0.2.dist-info/top_level.txt
pylmod-1.0.2.dist-info/zip-safe
pylmod-1.0.2.dist-info/RECORD
