Metadata-Version: 2.1
Name: pylmod
Version: 1.0.2
Summary: PyLmod is a Python Implementation of MIT Learning Modules
Home-page: http://github.com/mitodl/pylmod
Author: MIT ODL Engineering
Author-email: odl-engineering@mit.edu
License: BSD
Platform: UNKNOWN
Classifier: Development Status :: 5 - Production/Stable
Classifier: Intended Audience :: Developers
Classifier: Intended Audience :: Education
Classifier: Programming Language :: Python
Requires-Dist: requests (~=2.0)
Provides-Extra: dev
Requires-Dist: pytest (~=5.0) ; extra == 'dev'
Requires-Dist: pytest-cov (~=2.0) ; extra == 'dev'
Requires-Dist: pytest-flakes (~=4.0) ; extra == 'dev'
Requires-Dist: pytest-pep8 (~=1.0) ; extra == 'dev'
Requires-Dist: pytest-cache (~=1.0) ; extra == 'dev'
Requires-Dist: httpretty (~=0.9.0) ; extra == 'dev'
Requires-Dist: semantic-version (~=2.0) ; extra == 'dev'
Requires-Dist: mock (~=3.0) ; extra == 'dev'
Requires-Dist: ddt (~=1.0) ; extra == 'dev'
Provides-Extra: doc
Requires-Dist: sphinx (~=2.0) ; extra == 'doc'
Requires-Dist: sphinx-bootstrap-theme (==0.7.0) ; extra == 'doc'
Requires-Dist: sphinxcontrib-napoleon (==0.7) ; extra == 'doc'
